pyalc7t/__init__.py
pyalc7t/alcconfig.py
pyalc7t/alccore.py
pyalc7t/alckanal.py
pyalc7t/alcplot.py
pyalc7t/alcrs232.py
pyalc7t/alcthread.py
pyalc7t/alcwidgets.py
pyalc7t/pyalc7tmain.py
pyalc7t/userconfig.py
pyalc7t/Manual/changelog.html
pyalc7t/Manual/channelmenu.html
pyalc7t/Manual/filemenu.html
pyalc7t/Manual/helpmenu.html
pyalc7t/Manual/index.html
pyalc7t/Manual/interface.html
pyalc7t/Manual/introduction.html
pyalc7t/Manual/license.html
pyalc7t/Manual/miscellaneous.html
pyalc7t/Manual/processing.html
pyalc7t/Manual/releasenotes.html
pyalc7t/Manual/startup.html
pyalc7t/Manual/troubleshooting.html
pyalc7t/Manual/css/w3-theme-black.css
pyalc7t/Manual/css/w3.css
pyalc7t-1.1.1.dist-info/METADATA
pyalc7t-1.1.1.dist-info/WHEEL
pyalc7t-1.1.1.dist-info/entry_points.txt
pyalc7t-1.1.1.dist-info/licenses/LICENSE
pyalc7t-1.1.1.dist-info/RECORD
