Metadata-Version: 2.1
Name: pyalc7t
Version: 1.1.1
Summary: Control program and data logger for the ELV ALC7000 charger
Author: Joachim Siebold
Author-email: bug400@gmx.de
License:                     GNU GENERAL PUBLIC LICENSE
License-File: LICENSE
Classifier: Development Status :: 5 - Production/Stable
Classifier: License :: OSI Approved :: GNU General Public License v2 (GPLv2)
Classifier: Programming Language :: Python :: 3
Classifier: Programming Language :: Python :: 3.6
Classifier: Programming Language :: Python :: 3.7
Classifier: Programming Language :: Python :: 3.8
Classifier: Programming Language :: Python :: 3.9
Classifier: Programming Language :: Python :: 3.10
Classifier: Programming Language :: Python :: 3.11
Classifier: Programming Language :: Python :: 3.12
Classifier: Topic :: Utilities
Requires-Python: >=3.6
Requires-Dist: pyserial
Requires-Dist: pyside6
